Metadata-Version: 1.1
Name: ccpc
Version: 0.0.1
Summary: Chaotic Cable Pulling Chimp
Home-page: https://github.com/panagiks/CCPC
Author: panagiks
Author-email: UNKNOWN
License: MIT
Download-URL: https://github.com/panagiks/CCPC/archive/0.0.1.tar.gz
Keywords: ccpc open shift monkey chaos async OpenShift pod origin
Platform: UNKNOWN
Classifier: Development Status :: 4 - Beta
Classifier: License :: OSI Approved :: MIT License
Classifier: Programming Language :: Python :: 3.5
Classifier: Programming Language :: Python :: 3.6
Classifier: Programming Language :: Python :: 3.7
Classifier: Topic :: Security
Classifier: Operating System :: POSIX
Classifier: Operating System :: Unix
Classifier: Operating System :: Microsoft :: Windows
Classifier: Operating System :: MacOS
